dustgoggles/__init__.py
dustgoggles/composition.py
dustgoggles/dynamic.py
dustgoggles/func.py
dustgoggles/mosaic.py
dustgoggles/pivot.py
dustgoggles/scrape.py
dustgoggles/structures.py
dustgoggles/tracker.py
dustgoggles/codex/__init__.py
dustgoggles/codex/_array_holding_area.py
dustgoggles/codex/codecs.py
dustgoggles/codex/implements.py
dustgoggles/codex/memutilz.py
dustgoggles/test_utils/__init__.py
dustgoggles/test_utils/core.py
dustgoggles-0.7.6.dist-info/LICENSE
dustgoggles-0.7.6.dist-info/METADATA
dustgoggles-0.7.6.dist-info/WHEEL
dustgoggles-0.7.6.dist-info/top_level.txt
dustgoggles-0.7.6.dist-info/RECORD
